commandpool.py
commandpool-0.0.0.dist-info/DESCRIPTION.rst
commandpool-0.0.0.dist-info/METADATA
commandpool-0.0.0.dist-info/RECORD
commandpool-0.0.0.dist-info/WHEEL
commandpool-0.0.0.dist-info/metadata.json
commandpool-0.0.0.dist-info/top_level.txt
commandpool-0.0.0.dist-info/zip-safe
