Metadata-Version: 2.0
Name: commandpool
Version: 0.0.0
Summary: Functions for running many subprocesses in parallel
Home-page: https://github.com/gvalkov/python-commandpool
Author: Georgi Valkov
Author-email: georgi.t.valkov@gmail.com
License: Revised BSD License
Keywords: subprocess pool
Platform: UNKNOWN
Classifier: Development Status :: 5 - Production/Stable
Classifier: Programming Language :: Python :: 2.7
Classifier: Programming Language :: Python :: 3
Classifier: Programming Language :: Python :: 3.3
Classifier: Programming Language :: Python :: 3.4
Classifier: Programming Language :: Python :: 3.5
Classifier: Programming Language :: Python :: 3.6
Classifier: Intended Audience :: Developers
Classifier: Topic :: Software Development :: Libraries
Classifier: License :: OSI Approved :: BSD License
Provides-Extra: devel
Requires-Dist: bumpversion (>=0.5.2); extra == 'devel'
Requires-Dist: check-manifest (>=0.35); extra == 'devel'
Requires-Dist: readme-renderer (>=16.0); extra == 'devel'
Requires-Dist: flake8; extra == 'devel'
Requires-Dist: pep8-naming; extra == 'devel'
Provides-Extra: test
Requires-Dist: tox (>=2.6.0); extra == 'test'
Requires-Dist: pytest (>=3.0.3); extra == 'test'
Requires-Dist: pytest-cov (>=2.3.1); extra == 'test'
